qdigitalmeter/__init__.py
qdigitalmeter/qdigitalmeter.py
qdigitalmeter/scales.py
qdigitalmeter-0.1.0.dist-info/LICENSE
qdigitalmeter-0.1.0.dist-info/METADATA
qdigitalmeter-0.1.0.dist-info/WHEEL
qdigitalmeter-0.1.0.dist-info/RECORD
