Metadata-Version: 2.1
Name: qdigitalmeter
Version: 0.1.0
Summary: A simple digital peak meter for use with PyQt5, PyQt6, PySide2, and PySide6
Home-page: https://github.com/FrancescoCeruti/QDigitalMeter
License: LGPL-2.1-or-later
Author: Francesco Ceruti
Author-email: ceppofrancy@gmail.com
Requires-Python: >=3.8,<4.0
Classifier: License :: OSI Approved
Classifier: Programming Language :: Python :: 3
Classifier: Programming Language :: Python :: 3.8
Classifier: Programming Language :: Python :: 3.9
Classifier: Programming Language :: Python :: 3.10
Classifier: Programming Language :: Python :: 3.11
Classifier: Programming Language :: Python :: 3.12
Requires-Dist: qtpy (>=2.4,<3.0)
Project-URL: Repository, https://github.com/FrancescoCeruti/QDigitalMeter
